ra_trivial/ReportExport.py
ra_trivial/__init__.py
ra_trivial/__tests01.py
ra_trivial/__tests02.py
ra_trivial/__tests03.py
ra_trivial/__tests04.py
ra_trivial/__tests05.py
ra_trivial/__tests07.py
ra_trivial/trivial.py
ra_trivial-0.0.5.dist-info/LICENSE
ra_trivial-0.0.5.dist-info/METADATA
ra_trivial-0.0.5.dist-info/WHEEL
ra_trivial-0.0.5.dist-info/top_level.txt
ra_trivial-0.0.5.dist-info/RECORD
