Metadata-Version: 2.1
Name: ra-trivial
Version: 0.0.5
Summary: Diverence metric
Home-page: https://github.com/RachelAlcraft/MultiDimensionalAssociations
Author: Rachel Alcraft
Author-email: rachelalcraft@gmail.com
Project-URL: Bug Tracker, https://github.com/RachelAlcraft/MultiDimensionalAssociations/issues
Classifier: Programming Language :: Python :: 3
Classifier: License :: OSI Approved :: MIT License
Classifier: Operating System :: OS Independent
Requires-Python: >=3.6
License-File: LICENSE
